MANIFEST.in
README.md
opae.cpp
pycontext.cpp
pycontext.h
pyerrors.cpp
pyerrors.h
pyevents.cpp
pyevents.h
pyhandle.cpp
pyhandle.h
pyproperties.cpp
pyproperties.h
pyshared_buffer.cpp
pyshared_buffer.h
pysysobject.cpp
pysysobject.h
pytoken.cpp
pytoken.h
setup.py
opae/__init__.py
opae.fpga.egg-info/PKG-INFO
opae.fpga.egg-info/SOURCES.txt
opae.fpga.egg-info/dependency_links.txt
opae.fpga.egg-info/entry_points.txt
opae.fpga.egg-info/requires.txt
opae.fpga.egg-info/top_level.txt
opae/fpga/__init__.py