Metadata-Version: 1.0
Name: opae.fpga
Version: 1.2.0
Summary: pyopae provides Python bindings around the OPAE C API
Home-page: https://01.org/OPAE
Author: UNKNOWN
Author-email: UNKNOWN
License: BSD3
Keywords: OPAE accelerator fpga bindings
Platform: UNKNOWN
